setup.py
guippy/__init__.py
guippy/api.py
guippy/application.py
guippy/clipboard.py
guippy/decorator.py
guippy/error.py
guippy/guippy.py
guippy/keyboard.py
guippy/mouse.py
guippy/shortcut.py
guippy/util.py
guippy/window.py
guippy.egg-info/PKG-INFO
guippy.egg-info/SOURCES.txt
guippy.egg-info/dependency_links.txt
guippy.egg-info/top_level.txt
test/test_guippy.py